abstract_telegram_processor/__init__.py
abstract_telegram_processor-0.3.dist-info/LICENSE
abstract_telegram_processor-0.3.dist-info/METADATA
abstract_telegram_processor-0.3.dist-info/WHEEL
abstract_telegram_processor-0.3.dist-info/top_level.txt
abstract_telegram_processor-0.3.dist-info/RECORD
