Metadata-Version: 2.1
Name: abstract-telegram-processor
Version: 0.3
Summary: Abstract telegram processor.
Home-page: https://github.com/yababay/abstract-telegram-processor
Download-URL: https://github.com/yababay/abstract-telegram-processor/archive/v_01.tar.gz
Author: Михаил Беляков (Michael Belyakov)
Author-email: bigbelk@live.ru
License: MIT
Keywords: Telegram,bot,command
Platform: UNKNOWN
Classifier: Development Status :: 3 - Alpha
Classifier: Intended Audience :: Developers
Classifier: Topic :: Software Development :: Build Tools
Classifier: License :: OSI Approved :: MIT License
Classifier: Programming Language :: Python :: 3.9
License-File: LICENSE
Requires-Dist: emoji
Requires-Dist: yc-event-to-json
Requires-Dist: telegram-admin-informer
